requests_crawler/__about__.py
requests_crawler/__init__.py
requests_crawler/core.py
requests_crawler/core_bak.py
requests_crawler/crawler.py
requests_crawler/default_config.py
requests_crawler-0.5.4.dist-info/METADATA
requests_crawler-0.5.4.dist-info/RECORD
requests_crawler-0.5.4.dist-info/WHEEL
requests_crawler-0.5.4.dist-info/entry_points.txt
requests_crawler-0.5.4.dist-info/top_level.txt
webcrawler/__init__.py
webcrawler/core.py
webcrawler/default_config.yml
webcrawler/helpers.py
webcrawler/url_queue.py
