Metadata-Version: 2.1
Name: requests-crawler
Version: 0.5.4
Summary: A web crawler based on requests-html, mainly targets for url validation test.
Home-page: https://github.com/debugtalk/webcrawler
Author: debugtalk
Author-email: mail@debugtalk.com
License: MIT
Keywords: web crawler validation
Platform: UNKNOWN
Classifier: Programming Language :: Python :: 3.6
Requires-Dist: termcolor
Requires-Dist: requests-html
